kspconfig/__init__.py
kspconfig/kspconfig.py
kspconfig-1.3.dist-info/METADATA
kspconfig-1.3.dist-info/WHEEL
kspconfig-1.3.dist-info/top_level.txt
kspconfig-1.3.dist-info/RECORD
