Metadata-Version: 2.1
Name: kspconfig
Version: 1.3
Summary: Kerbal Space Program Craft and Cfg Loader
Home-page: https://github.com/Penta0308/kspconfig-python
Author: Penta0308
Author-email: kevin03088@naver.com
License: UNKNOWN
Platform: UNKNOWN
Classifier: Programming Language :: Python :: 3
Classifier: License :: OSI Approved :: MIT License
Classifier: Operating System :: OS Independent
Requires-Python: >=3.5
